auth_trial/__init__.py
auth_trial/auth.py
auth_trial/client.yaml
auth_trial-0.1.4.dist-info/METADATA
auth_trial-0.1.4.dist-info/WHEEL
auth_trial-0.1.4.dist-info/RECORD
