Metadata-Version: 2.1
Name: auth-trial
Version: 0.1.4
Summary: Auth Microservice (DTaaS) Package
Author: Asti
Author-email: f20190640@goa.bits-pilani.ac.in
Requires-Python: >=3.10,<4.0
Classifier: Programming Language :: Python :: 3
Classifier: Programming Language :: Python :: 3.10
Classifier: Programming Language :: Python :: 3.11
Classifier: Programming Language :: Python :: 3.12
Requires-Dist: pyyaml (>=6.0.1,<7.0.0)
Requires-Dist: requests-oauthlib (>=1.3.1,<2.0.0)
